ofx.py
setup.py
ofx.egg-info/PKG-INFO
ofx.egg-info/SOURCES.txt
ofx.egg-info/dependency_links.txt
ofx.egg-info/entry_points.txt
ofx.egg-info/requires.txt
ofx.egg-info/top_level.txt