Metadata-Version: 1.1
Name: ofx
Version: 0.1
Summary: Commandline tool for managing addons in OpenFrameworks
Home-page: https://github.com/HalfdanJ/ofx
Author: Jonas Jongejan
Author-email: ofx@halfdanj.dk
License: UNKNOWN
Download-URL: https://github.com/HalfdanJ/ofx/tarball/0.1
Platform: UNKNOWN
Classifier: Operating System :: OS Independent
Classifier: Intended Audience :: Developers
Classifier: Development Status :: 3 - Alpha
Classifier: Topic :: Utilities
